fastlexrank/FastLexRank.py
fastlexrank/__init__.py
fastlexrank-0.1.4.dist-info/LICENSE
fastlexrank-0.1.4.dist-info/METADATA
fastlexrank-0.1.4.dist-info/WHEEL
fastlexrank-0.1.4.dist-info/RECORD
