Metadata-Version: 2.1
Name: fastlexrank
Version: 0.1.4
Summary: A streamlined and approximate implementation of the LexRank algorithm for rapid text summarization.
License: Apache-2.0
Author: Mao Li
Author-email: maolee@umich.edu
Requires-Python: >=3.10,<4.0
Classifier: License :: OSI Approved :: Apache Software License
Classifier: Programming Language :: Python :: 3
Classifier: Programming Language :: Python :: 3.10
Classifier: Programming Language :: Python :: 3.11
Requires-Dist: numpy (>=1.20.0,<2.0.0)
Requires-Dist: sentence-transformers (>=2.2.2,<3.0.0)
